pytest_xtime.py
pytest_xtime-0.0.1.dist-info/METADATA
pytest_xtime-0.0.1.dist-info/WHEEL
pytest_xtime-0.0.1.dist-info/entry_points.txt
pytest_xtime-0.0.1.dist-info/licenses/LICENSE
pytest_xtime-0.0.1.dist-info/RECORD
